justjit/_core.cp313-win_amd64.pyd
justjit/__init__.py
justjit/vendor/libc-headers/aio.h
justjit/vendor/libc-headers/alloca.h
justjit/vendor/libc-headers/ar.h
justjit/vendor/libc-headers/assert.h
justjit/vendor/libc-headers/byteswap.h
justjit/vendor/libc-headers/complex.h
justjit/vendor/libc-headers/cpio.h
justjit/vendor/libc-headers/crypt.h
justjit/vendor/libc-headers/ctype.h
justjit/vendor/libc-headers/dirent.h
justjit/vendor/libc-headers/dlfcn.h
justjit/vendor/libc-headers/elf.h
justjit/vendor/libc-headers/endian.h
justjit/vendor/libc-headers/err.h
justjit/vendor/libc-headers/errno.h
justjit/vendor/libc-headers/fcntl.h
justjit/vendor/libc-headers/features.h
justjit/vendor/libc-headers/fenv.h
justjit/vendor/libc-headers/float.h
justjit/vendor/libc-headers/fmtmsg.h
justjit/vendor/libc-headers/fnmatch.h
justjit/vendor/libc-headers/ftw.h
justjit/vendor/libc-headers/getopt.h
justjit/vendor/libc-headers/glob.h
justjit/vendor/libc-headers/grp.h
justjit/vendor/libc-headers/iconv.h
justjit/vendor/libc-headers/ifaddrs.h
justjit/vendor/libc-headers/inttypes.h
justjit/vendor/libc-headers/iso646.h
justjit/vendor/libc-headers/langinfo.h
justjit/vendor/libc-headers/lastlog.h
justjit/vendor/libc-headers/libgen.h
justjit/vendor/libc-headers/libintl.h
justjit/vendor/libc-headers/limits.h
justjit/vendor/libc-headers/link.h
justjit/vendor/libc-headers/locale.h
justjit/vendor/libc-headers/malloc.h
justjit/vendor/libc-headers/math.h
justjit/vendor/libc-headers/memory.h
justjit/vendor/libc-headers/mntent.h
justjit/vendor/libc-headers/monetary.h
justjit/vendor/libc-headers/mqueue.h
justjit/vendor/libc-headers/netdb.h
justjit/vendor/libc-headers/nl_types.h
justjit/vendor/libc-headers/paths.h
justjit/vendor/libc-headers/poll.h
justjit/vendor/libc-headers/pthread.h
justjit/vendor/libc-headers/pty.h
justjit/vendor/libc-headers/pwd.h
justjit/vendor/libc-headers/regex.h
justjit/vendor/libc-headers/resolv.h
justjit/vendor/libc-headers/sched.h
justjit/vendor/libc-headers/search.h
justjit-0.1.6.dist-info/DELVEWHEEL
justjit-0.1.6.dist-info/METADATA
justjit-0.1.6.dist-info/RECORD
justjit-0.1.6.dist-info/WHEEL
justjit-0.1.6.dist-info/licenses/LICENSE
