Metadata-Version: 2.4
Name: justjit
Version: 0.1.6
Summary: Fast Python JIT compiler using LLVM ORC - lowers Python bytecode to native machine code
Keywords: jit,compiler,llvm,python,optimization,performance
Author-Email: Magi8101 <sharmamagi0@gmail.com>
License-Expression: Apache-2.0
Classifier: Development Status :: 3 - Alpha
Classifier: Intended Audience :: Developers
Classifier: Programming Language :: Python :: 3
Classifier: Programming Language :: Python :: 3.13
Classifier: Programming Language :: C++
Classifier: Topic :: Software Development :: Compilers
Classifier: Topic :: Software Development :: Code Generators
Project-URL: Homepage, https://github.com/magi8101/justjit
Project-URL: Repository, https://github.com/magi8101/justjit
Project-URL: Documentation, https://justjit.readthedocs.io/en/latest/
Requires-Python: >=3.13
Requires-Dist: numpy
